setup.py
Flask_Douwa.egg-info/PKG-INFO
Flask_Douwa.egg-info/SOURCES.txt
Flask_Douwa.egg-info/dependency_links.txt
Flask_Douwa.egg-info/not-zip-safe
Flask_Douwa.egg-info/requires.txt
Flask_Douwa.egg-info/top_level.txt
flask_douwa/__init__.py
flask_douwa/cache.py
flask_douwa/decorators.py
flask_douwa/kafka_broker.py
flask_douwa/kafka_broker_bak.py
flask_douwa/kafka_brokerc.py
flask_douwa/reqparse.py
flask_douwa/routes.py
flask_douwa/protoparser/__init__.py
flask_douwa/protoparser/exc.py
flask_douwa/protoparser/grammar.py
flask_douwa/protoparser/lexer.py
flask_douwa/protoparser/objects.py
flask_douwa/protoparser/parser.py
flask_douwa/rpc/__init__.py
flask_douwa/rpc/demo.py
flask_douwa/rpc/generator_id.py
flask_douwa/rpc/type.py
flask_douwa/rpc_client/__init__.py
flask_douwa/rpc_client/greeter_client.py
flask_douwa/rpc_client/rpc_data_pb2.py
flask_douwa/rpc_client/rpc_data_pb2_grpc.py
flask_douwa/rpc_client/rpc_permission.py
sequence_field/__init__.py
sequence_field/constants.py
sequence_field/expanders.py
sequence_field/fields.py
sequence_field/models.py
sequence_field/settings.py
sequence_field/strings.py
sequence_field/utils.py