Metadata-Version: 1.1
Name: Flask-Douwa
Version: 1.2.0
Summary: 一个flask插件
Home-page: UNKNOWN
Author: jhchen
Author-email: watasihakamidesu@sina.cn
License: MIT
Platform: any
Classifier: Framework :: Flask
Classifier: Natural Language :: English
Classifier: Environment :: Web Environment
Classifier: Intended Audience :: Developers
Classifier: License :: OSI Approved :: MIT License
Classifier: Operating System :: OS Independent
Classifier: Programming Language :: Python
Classifier: Topic :: Internet :: WWW/HTTP :: Dynamic Content
Classifier: Topic :: Software Development :: Libraries :: Python Modules
